{"latitude":38.8048,"longitude":-77.0469,"timezone":"America/New_York","offset":-4,"currently":{"time":273430800,"summary":"Mostly Cloudy","icon":"partly-cloudy-day","precipIntensity":0,"precipProbability":0,"temperature":83.06,"apparentTemperature":89.18,"dewPoint":73.26,"humidity":0.72,"windSpeed":6.83,"windBearing":206,"visibility":4.8,"cloudCover":0.92,"pressure":1016.61},"hourly":{"summary":"Light rain in the evening.","icon":"rain","data":[{"time":273384000,"summary":"Overcast","icon":"cloudy","precipType":"rain","temperature":72.02,"apparentTemperature":72.02,"dewPoint":68.49,"humidity":0.89,"windSpeed":4.4,"windBearing":78,"visibility":5.64,"cloudCover":1,"pressure":1018},{"time":273387600,"summary":"Rain","icon":"rain","precipIntensity":0.06,"precipProbability":1,"precipType":"rain","temperature":73.53,"apparentTemperature":73.53,"dewPoint":70.23,"humidity":0.89,"windSpeed":6.91,"windBearing":125,"visibility":6.97,"cloudCover":1,"pressure":1018.22},{"time":273391200,"summary":"Overcast","icon":"cloudy","precipIntensity":0,"precipProbability":0,"temperature":73.16,"apparentTemperature":73.16,"dewPoint":70.4,"humidity":0.91,"windSpeed":4,"windBearing":180,"visibility":8.3,"cloudCover":1,"pressure":1017.28},{"time":273394800,"summary":"Overcast","icon":"cloudy","precipIntensity":0,"precipProbability":0,"temperature":72.98,"apparentTemperature":72.98,"dewPoint":70.04,"humidity":0.91,"windSpeed":5.7,"windBearing":192,"visibility":7.94,"cloudCover":1,"pressure":1016.88},{"time":273398400,"summary":"Overcast","icon":"cloudy","precipIntensity":0,"precipProbability":0,"temperature":72.91,"apparentTemperature":72.91,"dewPoint":69.86,"humidity":0.9,"windSpeed":7.15,"windBearing":186,"visibility":7.94,"cloudCover":1,"pressure":1016.61},{"time":273402000,"summary":"Overcast","icon":"cloudy","precipIntensity":0,"precipProbability":0,"temperature":72.52,"apparentTemperature":72.52,"dewPoint":70.83,"humidity":0.94,"windSpeed":6.23,"windBearing":197,"visibility":6.8,"cloudCover":1,"pressure":1016.56},{"time":273405600,"summary":"Overcast","icon":"cloudy","precipIntensity":0,"precipProbability":0,"temperature":73.38,"apparentTemperature":73.38,"dewPoint":70.92,"humidity":0.92,"windSpeed":2.33,"windBearing":250,"visibility":6.88,"cloudCover":1,"pressure":1016.83},{"time":273409200,"summary":"Mostly Cloudy","icon":"partly-cloudy-day","precipType":"rain","temperature":73.73,"apparentTemperature":73.73,"dewPoint":70.54,"humidity":0.9,"windSpeed":5.92,"windBearing":212,"visibility":3.84,"cloudCover":0.92,"pressure":1016.57},{"time":273412800,"summary":"Mostly Cloudy","icon":"partly-cloudy-day","precipIntensity":0,"precipProbability":0,"temperature":74.68,"apparentTemperature":74.68,"dewPoint":71.24,"humidity":0.89,"windSpeed":7.64,"windBearing":195,"visibility":3.42,"cloudCover":0.92,"pressure":1016.24},{"time":273416400,"summary":"Mostly Cloudy","icon":"partly-cloudy-day","precipIntensity":0,"precipProbability":0,"temperature":76.17,"apparentTemperature":76.17,"dewPoint":72.09,"humidity":0.87,"windSpeed":8.9,"windBearing":201,"visibility":3.72,"cloudCover":0.92,"pressure":1016.61},{"time":273420000,"summary":"Mostly Cloudy","icon":"partly-cloudy-day","precipIntensity":0,"precipProbability":0,"temperature":78.28,"apparentTemperature":78.28,"dewPoint":72.72,"humidity":0.83,"windSpeed":8.43,"windBearing":229,"visibility":4.55,"cloudCover":0.88,"pressure":1016.61},{"time":273423600,"summary":"Mostly Cloudy","icon":"partly-cloudy-day","precipIntensity":0,"precipProbability":0,"temperature":79.89,"apparentTemperature":79.89,"dewPoint":72.86,"humidity":0.79,"windSpeed":7.86,"windBearing":216,"visibility":4.83,"cloudCover":0.92,"pressure":1016.8},{"time":273427200,"summary":"Mostly Cloudy","icon":"partly-cloudy-day","precipIntensity":0,"precipProbability":0,"temperature":80.67,"apparentTemperature":85.2,"dewPoint":72.8,"humidity":0.77,"windSpeed":6.16,"windBearing":204,"visibility":5.31,"cloudCover":0.92,"pressure":1016.88},{"time":273430800,"summary":"Mostly Cloudy","icon":"partly-cloudy-day","precipIntensity":0,"precipProbability":0,"temperature":83.06,"apparentTemperature":89.18,"dewPoint":73.26,"humidity":0.72,"windSpeed":6.83,"windBearing":206,"visibility":4.8,"cloudCover":0.92,"pressure":1016.61},{"time":273434400,"summary":"Mostly Cloudy","icon":"partly-cloudy-day","precipIntensity":0,"precipProbability":0,"temperature":83.67,"apparentTemperature":90.06,"dewPoint":73.23,"humidity":0.71,"windSpeed":6.94,"windBearing":223,"visibility":5.31,"cloudCover":0.92,"pressure":1016.24},{"time":273438000,"summary":"Overcast","icon":"cloudy","precipIntensity":0,"precipProbability":0,"temperature":84.25,"apparentTemperature":91.27,"dewPoint":73.69,"humidity":0.71,"windSpeed":5.7,"windBearing":235,"visibility":5.09,"cloudCover":1,"pressure":1015.67},{"time":273441600,"summary":"Overcast","icon":"cloudy","precipIntensity":0,"precipProbability":0,"temperature":83.66,"apparentTemperature":90.43,"dewPoint":73.74,"humidity":0.72,"windSpeed":6.29,"windBearing":182,"visibility":5.48,"cloudCover":0.97,"pressure":1015.2},{"time":273445200,"summary":"Light Rain","icon":"rain","precipIntensity":0.01,"precipProbability":1,"precipType":"rain","temperature":79.37,"apparentTemperature":79.37,"dewPoint":72.01,"humidity":0.78,"windSpeed":6.76,"windBearing":242,"visibility":4.73,"cloudCover":0.97,"pressure":1014.79},{"time":273448800,"summary":"Light Rain","icon":"rain","precipIntensity":0.02,"precipProbability":1,"precipType":"rain","temperature":78.05,"apparentTemperature":78.05,"dewPoint":73,"humidity":0.85,"windSpeed":5.56,"windBearing":185,"visibility":5.43,"cloudCover":0.97,"pressure":1014.9},{"time":273452400,"summary":"Mostly Cloudy","icon":"partly-cloudy-day","precipType":"rain","temperature":76.66,"apparentTemperature":76.66,"dewPoint":73.08,"humidity":0.89,"windSpeed":3.54,"windBearing":177,"visibility":4.05,"cloudCover":0.86,"pressure":1014.6},{"time":273456000,"summary":"Overcast","icon":"cloudy","precipIntensity":0,"precipProbability":0,"temperature":76.93,"apparentTemperature":76.93,"dewPoint":72.28,"humidity":0.86,"windSpeed":5.13,"windBearing":186,"visibility":4.1,"cloudCover":1,"pressure":1015.16},{"time":273459600,"summary":"Overcast","icon":"cloudy","precipIntensity":0,"precipProbability":0,"temperature":76.25,"apparentTemperature":76.25,"dewPoint":72.32,"humidity":0.88,"windSpeed":5.96,"windBearing":190,"visibility":5.54,"cloudCover":1,"pressure":1015.87},{"time":273463200,"summary":"Overcast","icon":"cloudy","precipIntensity":0,"precipProbability":0,"temperature":75.48,"apparentTemperature":75.48,"dewPoint":72.43,"humidity":0.9,"windSpeed":7,"windBearing":220,"visibility":7.88,"cloudCover":1,"pressure":1015.89},{"time":273466800,"summary":"Overcast","icon":"cloudy","precipIntensity":0,"precipProbability":0,"temperature":75.16,"apparentTemperature":75.16,"dewPoint":71.85,"humidity":0.89,"windSpeed":7.72,"windBearing":226,"visibility":7.62,"cloudCover":1,"pressure":1016.25}]},"daily":{"data":[{"time":273384000,"summary":"Light rain in the evening.","icon":"rain","sunriseTime":273407886,"sunsetTime":273454902,"moonPhase":0.93,"precipIntensity":0.0043,"precipType":"rain","temperatureMin":72.02,"temperatureMinTime":273384000,"temperatureMax":84.25,"temperatureMaxTime":273438000,"apparentTemperatureMin":72.02,"apparentTemperatureMinTime":273384000,"apparentTemperatureMax":91.27,"apparentTemperatureMaxTime":273438000,"dewPoint":71.83,"humidity":0.85,"windSpeed":5.37,"windBearing":202,"visibility":5.67,"cloudCover":0.96,"pressure":1016.3}]},"flags":{"sources":["isd"],"isd-stations":["722244-99999","724030-93738","724037-93728","724050-13743","745940-13705"],"units":"us"}}