{"latitude":38.8048,"longitude":-77.0469,"timezone":"America/New_York","offset":-4,"currently":{"time":898707600,"summary":"Mostly Cloudy","icon":"partly-cloudy-day","precipIntensity":0,"precipProbability":0,"temperature":83.64,"apparentTemperature":89.09,"dewPoint":71.91,"humidity":0.68,"windSpeed":6.24,"windBearing":11,"visibility":5.54,"cloudCover":0.77,"pressure":1018.82},"hourly":{"summary":"Mostly cloudy until evening.","icon":"partly-cloudy-day","data":[{"time":898660800,"summary":"Rain","icon":"rain","precipIntensity":0.06,"precipProbability":1,"precipType":"rain","temperature":73.33,"apparentTemperature":73.33,"dewPoint":71.26,"humidity":0.93,"windSpeed":0.96,"windBearing":149,"visibility":2.84,"cloudCover":0.98,"pressure":1016.71},{"time":898664400,"summary":"Overcast","icon":"cloudy","precipIntensity":0,"precipProbability":0,"temperature":73.11,"apparentTemperature":73.11,"dewPoint":71.31,"humidity":0.94,"windSpeed":3.06,"windBearing":301,"visibility":3.28,"cloudCover":0.98,"pressure":1016.28},{"time":898668000,"summary":"Overcast","icon":"cloudy","precipIntensity":0,"precipProbability":0,"temperature":73.04,"apparentTemperature":73.04,"dewPoint":71.91,"humidity":0.96,"windSpeed":3.32,"windBearing":356,"visibility":3.35,"cloudCover":0.95,"pressure":1016.45},{"time":898671600,"summary":"Overcast","icon":"cloudy","precipIntensity":0,"precipProbability":0,"temperature":72.97,"apparentTemperature":72.97,"dewPoint":71.18,"humidity":0.94,"windSpeed":4.41,"windBearing":316,"visibility":2.67,"cloudCover":0.98,"pressure":1016.55},{"time":898675200,"summary":"Overcast","icon":"cloudy","precipIntensity":0,"precipProbability":0,"temperature":72.91,"apparentTemperature":72.91,"dewPoint":71.2,"humidity":0.94,"windSpeed":6.56,"windBearing":334,"visibility":3.12,"cloudCover":0.98,"pressure":1016.31},{"time":898678800,"summary":"Overcast","icon":"cloudy","precipIntensity":0,"precipProbability":0,"temperature":72.45,"apparentTemperature":72.45,"dewPoint":70.04,"humidity":0.92,"windSpeed":4.17,"windBearing":339,"visibility":3.73,"cloudCover":1,"pressure":1016.51},{"time":898682400,"summary":"Mostly Cloudy","icon":"partly-cloudy-day","precipIntensity":0,"precipProbability":0,"temperature":72.04,"apparentTemperature":72.04,"dewPoint":69.5,"humidity":0.92,"windSpeed":3.82,"windBearing":351,"visibility":3.81,"cloudCover":0.78,"pressure":1016.67},{"time":898686000,"summary":"Partly Cloudy","icon":"partly-cloudy-day","precipIntensity":0,"precipProbability":0,"temperature":72.58,"apparentTemperature":72.58,"dewPoint":70.25,"humidity":0.92,"windSpeed":6.5,"windBearing":347,"visibility":4.06,"cloudCover":0.54,"pressure":1017.15},{"time":898689600,"summary":"Partly Cloudy","icon":"partly-cloudy-day","precipIntensity":0,"precipProbability":0,"temperature":74.62,"apparentTemperature":74.62,"dewPoint":70.43,"humidity":0.87,"windSpeed":7.03,"windBearing":345,"visibility":3.82,"cloudCover":0.44,"pressure":1017.93},{"time":898693200,"summary":"Partly Cloudy","icon":"partly-cloudy-day","precipIntensity":0,"precipProbability":0,"temperature":77.39,"apparentTemperature":77.39,"dewPoint":71.75,"humidity":0.83,"windSpeed":7.7,"windBearing":347,"visibility":4.77,"cloudCover":0.39,"pressure":1018.47},{"time":898696800,"summary":"Partly Cloudy","icon":"partly-cloudy-day","precipIntensity":0,"precipProbability":0,"temperature":79.19,"apparentTemperature":79.19,"dewPoint":71.67,"humidity":0.78,"windSpeed":6.68,"windBearing":347,"visibility":5.5,"cloudCover":0.34,"pressure":1018.45},{"time":898700400,"summary":"Mostly Cloudy","icon":"partly-cloudy-day","precipIntensity":0,"precipProbability":0,"temperature":80.39,"apparentTemperature":84.24,"dewPoint":71.56,"humidity":0.75,"windSpeed":9.7,"windBearing":357,"visibility":5.5,"cloudCover":0.65,"pressure":1018.8},{"time":898704000,"summary":"Mostly Cloudy","icon":"partly-cloudy-day","precipIntensity":0,"precipProbability":0,"temperature":82.97,"apparentTemperature":88.5,"dewPoint":72.41,"humidity":0.71,"windSpeed":9.69,"windBearing":11,"visibility":6,"cloudCover":0.68,"pressure":1018.79},{"time":898707600,"summary":"Mostly Cloudy","icon":"partly-cloudy-day","precipIntensity":0,"precipProbability":0,"temperature":83.64,"apparentTemperature":89.09,"dewPoint":71.91,"humidity":0.68,"windSpeed":6.24,"windBearing":11,"visibility":5.54,"cloudCover":0.77,"pressure":1018.82},{"time":898711200,"summary":"Partly Cloudy","icon":"partly-cloudy-day","precipIntensity":0,"precipProbability":0,"temperature":85.44,"apparentTemperature":91.79,"dewPoint":72.29,"humidity":0.65,"windSpeed":5.46,"windBearing":22,"visibility":6.37,"cloudCover":0.4,"pressure":1018.47},{"time":898714800,"summary":"Partly Cloudy","icon":"partly-cloudy-day","precipIntensity":0,"precipProbability":0,"temperature":86.15,"apparentTemperature":92.17,"dewPoint":71.61,"humidity":0.62,"windSpeed":7.75,"windBearing":24,"visibility":6.37,"cloudCover":0.44,"pressure":1017.91},{"time":898718400,"summary":"Partly Cloudy","icon":"partly-cloudy-day","precipIntensity":0,"precipProbability":0,"temperature":86.73,"apparentTemperature":91.88,"dewPoint":70.32,"humidity":0.58,"windSpeed":7.78,"windBearing":20,"visibility":6.84,"cloudCover":0.31,"pressure":1017.36},{"time":898722000,"summary":"Partly Cloudy","icon":"partly-cloudy-day","precipIntensity":0,"precipProbability":0,"temperature":86.8,"apparentTemperature":91.58,"dewPoint":69.81,"humidity":0.57,"windSpeed":4.87,"windBearing":49,"visibility":6.84,"cloudCover":0.31,"pressure":1017.13},{"time":898725600,"summary":"Partly Cloudy","icon":"partly-cloudy-day","precipIntensity":0,"precipProbability":0,"temperature":85.85,"apparentTemperature":90.36,"dewPoint":69.68,"humidity":0.59,"windSpeed":3.6,"windBearing":109,"visibility":6.84,"cloudCover":0.31,"pressure":1016.86},{"time":898729200,"summary":"Partly Cloudy","icon":"partly-cloudy-day","precipIntensity":0,"precipProbability":0,"temperature":85.65,"apparentTemperature":90.6,"dewPoint":70.37,"humidity":0.6,"windSpeed":1.99,"windBearing":105,"visibility":6.83,"cloudCover":0.34,"pressure":1016.78},{"time":898732800,"summary":"Partly Cloudy","icon":"partly-cloudy-day","precipIntensity":0,"precipProbability":0,"temperature":84.83,"apparentTemperature":90.65,"dewPoint":71.85,"humidity":0.65,"windSpeed":7.34,"windBearing":195,"visibility":5.77,"cloudCover":0.29,"pressure":1016.69},{"time":898736400,"summary":"Clear","icon":"clear-night","precipIntensity":0,"precipProbability":0,"temperature":80.14,"apparentTemperature":84.09,"dewPoint":72.2,"humidity":0.77,"windSpeed":4.17,"windBearing":175,"visibility":5.51,"cloudCover":0.22,"pressure":1017.66},{"time":898740000,"summary":"Clear","icon":"clear-night","precipIntensity":0,"precipProbability":0,"temperature":78.26,"apparentTemperature":78.26,"dewPoint":72.46,"humidity":0.82,"windSpeed":5.95,"windBearing":168,"visibility":4.87,"cloudCover":0.22,"pressure":1017.98},{"time":898743600,"summary":"Clear","icon":"clear-night","precipIntensity":0,"precipProbability":0,"temperature":77.26,"apparentTemperature":77.26,"dewPoint":73.65,"humidity":0.89,"windSpeed":4.77,"windBearing":196,"visibility":4.34,"cloudCover":0.17,"pressure":1018.06}]},"daily":{"data":[{"time":898660800,"summary":"Partly cloudy until evening.","icon":"partly-cloudy-day","sunriseTime":898681526,"sunsetTime":898735100,"moonPhase":0.02,"precipIntensity":0.0025,"precipIntensityMax":0.06,"precipIntensityMaxTime":898660800,"precipProbability":1,"precipType":"rain","temperatureMin":72.04,"temperatureMinTime":898682400,"temperatureMax":86.8,"temperatureMaxTime":898722000,"apparentTemperatureMin":72.04,"apparentTemperatureMinTime":898682400,"apparentTemperatureMax":91.58,"apparentTemperatureMaxTime":898722000,"dewPoint":71.28,"humidity":0.79,"windSpeed":3.02,"windBearing":1,"visibility":4.94,"cloudCover":0.56,"pressure":1017.45}]},"flags":{"sources":["isd"],"isd-stations":["724030-93738","724035-13773","724037-93728","724050-13743","745940-13705"],"units":"us"}}