{"latitude":38.8048,"longitude":-77.0469,"timezone":"America/New_York","offset":-4,"currently":{"time":923850000,"summary":"Light Rain","icon":"rain","precipIntensity":0.0134,"precipProbability":1,"precipType":"rain","temperature":49.34,"apparentTemperature":46.25,"dewPoint":46.97,"humidity":0.91,"windSpeed":7.34,"windBearing":84,"visibility":3.88,"cloudCover":1,"pressure":1014.14},"hourly":{"summary":"Rain starting in the morning, continuing until evening.","icon":"rain","data":[{"time":923803200,"summary":"Clear","icon":"clear-night","precipIntensity":0,"precipProbability":0,"temperature":48.03,"apparentTemperature":47.3,"dewPoint":35.79,"humidity":0.62,"windSpeed":3.17,"windBearing":139,"visibility":8.79,"cloudCover":0.05,"pressure":1018.62},{"time":923806800,"summary":"Clear","icon":"clear-night","precipIntensity":0,"precipProbability":0,"temperature":48.17,"apparentTemperature":48.17,"dewPoint":36.86,"humidity":0.65,"windSpeed":1.5,"windBearing":261,"visibility":8.79,"cloudCover":0.07,"pressure":1018.83},{"time":923810400,"summary":"Clear","icon":"clear-night","precipIntensity":0,"precipProbability":0,"temperature":47.24,"apparentTemperature":47.24,"dewPoint":36.3,"humidity":0.66,"windSpeed":1.18,"windBearing":67,"visibility":8.79,"cloudCover":0.15,"pressure":1018.6},{"time":923814000,"summary":"Mostly Cloudy","icon":"partly-cloudy-night","precipIntensity":0,"precipProbability":0,"temperature":46.97,"apparentTemperature":46.97,"dewPoint":36.44,"humidity":0.67,"windSpeed":2.41,"windBearing":132,"visibility":8.79,"cloudCover":0.62,"pressure":1018.15},{"time":923817600,"summary":"Mostly Cloudy","icon":"partly-cloudy-night","precipIntensity":0,"precipProbability":0,"temperature":47.61,"apparentTemperature":46.22,"dewPoint":38.95,"humidity":0.72,"windSpeed":3.87,"windBearing":146,"visibility":8.79,"cloudCover":0.8,"pressure":1018.17},{"time":923821200,"summary":"Mostly Cloudy","icon":"partly-cloudy-night","precipIntensity":0,"precipProbability":0,"temperature":48.25,"apparentTemperature":46.03,"dewPoint":40.3,"humidity":0.74,"windSpeed":5.2,"windBearing":111,"visibility":8.79,"cloudCover":0.9,"pressure":1017.58},{"time":923824800,"summary":"Overcast","icon":"cloudy","precipIntensity":0,"precipProbability":0,"temperature":49.13,"apparentTemperature":46.85,"dewPoint":42.23,"humidity":0.77,"windSpeed":5.59,"windBearing":101,"visibility":8.79,"cloudCover":0.96,"pressure":1017.47},{"time":923828400,"summary":"Drizzle","icon":"rain","precipIntensity":0.009,"precipProbability":0.11,"precipType":"rain","temperature":48.34,"apparentTemperature":48.34,"dewPoint":43.72,"humidity":0.84,"windSpeed":2.25,"windBearing":80,"visibility":8.15,"cloudCover":1,"pressure":1017.99},{"time":923832000,"summary":"Rain","icon":"rain","precipIntensity":0.1211,"precipProbability":1,"precipType":"rain","temperature":47.7,"apparentTemperature":47.7,"dewPoint":45.23,"humidity":0.91,"windSpeed":2.66,"windBearing":104,"visibility":6.8,"cloudCover":1,"pressure":1017.89},{"time":923835600,"summary":"Rain","icon":"rain","precipIntensity":0.0711,"precipProbability":1,"precipType":"rain","temperature":47.84,"apparentTemperature":45.34,"dewPoint":45.83,"humidity":0.93,"windSpeed":5.55,"windBearing":86,"visibility":5.4,"cloudCover":1,"pressure":1017.08},{"time":923839200,"summary":"Light Rain","icon":"rain","precipIntensity":0.0211,"precipProbability":1,"precipType":"rain","temperature":48.47,"apparentTemperature":45.42,"dewPoint":46.54,"humidity":0.93,"windSpeed":6.86,"windBearing":100,"visibility":6.62,"cloudCover":1,"pressure":1016.03},{"time":923842800,"summary":"Rain","icon":"rain","precipIntensity":0.1,"precipProbability":1,"precipType":"rain","temperature":48.48,"apparentTemperature":45.18,"dewPoint":46.81,"humidity":0.94,"windSpeed":7.38,"windBearing":72,"visibility":4.21,"cloudCover":1,"pressure":1016.27},{"time":923846400,"summary":"Light Rain","icon":"rain","precipIntensity":0.01,"precipProbability":1,"precipType":"rain","temperature":49,"apparentTemperature":44.84,"dewPoint":46.87,"humidity":0.92,"windSpeed":9.88,"windBearing":109,"visibility":4.44,"cloudCover":1,"pressure":1014.82},{"time":923850000,"summary":"Light Rain","icon":"rain","precipIntensity":0.0134,"precipProbability":1,"precipType":"rain","temperature":49.34,"apparentTemperature":46.25,"dewPoint":46.97,"humidity":0.91,"windSpeed":7.34,"windBearing":84,"visibility":3.88,"cloudCover":1,"pressure":1014.14},{"time":923853600,"summary":"Light Rain","icon":"rain","precipIntensity":0.01,"precipProbability":1,"precipType":"rain","temperature":50.14,"apparentTemperature":50.14,"dewPoint":45.8,"humidity":0.85,"windSpeed":10.72,"windBearing":124,"visibility":8.19,"cloudCover":1,"pressure":1012.07},{"time":923857200,"summary":"Overcast","icon":"cloudy","precipIntensity":0,"precipProbability":0,"temperature":49.74,"apparentTemperature":44.59,"dewPoint":44.79,"humidity":0.83,"windSpeed":13.9,"windBearing":149,"visibility":7.12,"cloudCover":1,"pressure":1009.92},{"time":923860800,"summary":"Overcast","icon":"cloudy","precipIntensity":0,"precipProbability":0,"temperature":48.81,"apparentTemperature":44.39,"dewPoint":45.66,"humidity":0.89,"windSpeed":10.49,"windBearing":149,"visibility":7.99,"cloudCover":1,"pressure":1008.4},{"time":923864400,"summary":"Overcast","icon":"cloudy","precipIntensity":0,"precipProbability":0,"temperature":48.34,"apparentTemperature":43.8,"dewPoint":46.24,"humidity":0.92,"windSpeed":10.52,"windBearing":159,"visibility":4.37,"cloudCover":1,"pressure":1007.57},{"time":923868000,"summary":"Overcast","icon":"cloudy","precipIntensity":0,"precipProbability":0,"temperature":48.27,"apparentTemperature":45.3,"dewPoint":46.4,"humidity":0.93,"windSpeed":6.61,"windBearing":127,"visibility":3.43,"cloudCover":1,"pressure":1007.6},{"time":923871600,"summary":"Drizzle","icon":"rain","precipIntensity":0.0089,"precipProbability":0.89,"precipType":"rain","temperature":47.94,"apparentTemperature":45.8,"dewPoint":47.22,"humidity":0.97,"windSpeed":5,"windBearing":76,"visibility":2.64,"cloudCover":1,"pressure":1007.21},{"time":923875200,"summary":"Light Rain","icon":"rain","precipIntensity":0.01,"precipProbability":1,"precipType":"rain","temperature":47.94,"apparentTemperature":45.54,"dewPoint":47.29,"humidity":0.98,"windSpeed":5.42,"windBearing":73,"visibility":5.32,"cloudCover":1,"pressure":1007.03},{"time":923878800,"summary":"Overcast","icon":"cloudy","precipIntensity":0,"precipProbability":0,"temperature":48.01,"apparentTemperature":44.85,"dewPoint":46.26,"humidity":0.94,"windSpeed":6.87,"windBearing":55,"visibility":6.51,"cloudCover":1,"pressure":1007.03},{"time":923882400,"summary":"Overcast","icon":"cloudy","precipIntensity":0,"precipProbability":0,"temperature":47.87,"apparentTemperature":44.49,"dewPoint":46.65,"humidity":0.95,"windSpeed":7.29,"windBearing":22,"visibility":4.77,"cloudCover":1,"pressure":1007.82},{"time":923886000,"summary":"Overcast","icon":"cloudy","precipIntensity":0,"precipProbability":0,"temperature":47.47,"apparentTemperature":43.25,"dewPoint":46.76,"humidity":0.97,"windSpeed":9.07,"windBearing":9,"visibility":3.79,"cloudCover":1,"pressure":1007.95}]},"daily":{"data":[{"time":923803200,"summary":"Rain until afternoon, starting again in the evening.","icon":"rain","sunriseTime":923827133,"sunsetTime":923874104,"moonPhase":0.84,"precipIntensity":0.0156,"precipIntensityMax":0.1211,"precipIntensityMaxTime":923832000,"precipProbability":1,"precipType":"rain","temperatureMin":46.97,"temperatureMinTime":923814000,"temperatureMax":50.14,"temperatureMaxTime":923853600,"apparentTemperatureMin":43.25,"apparentTemperatureMinTime":923886000,"apparentTemperatureMax":50.14,"apparentTemperatureMaxTime":923853600,"dewPoint":43.83,"humidity":0.85,"windSpeed":4.62,"windBearing":105,"visibility":6.47,"cloudCover":0.86,"pressure":1013.51}]},"flags":{"sources":["isd"],"isd-stations":["724030-93738","724035-13773","724037-93728","724050-13743","745940-13705"],"units":"us"}}