{"latitude":38.8048,"longitude":-77.0469,"timezone":"America/New_York","offset":-5,"currently":{"time":947264400,"summary":"Partly Cloudy","icon":"partly-cloudy-day","precipIntensity":0,"precipProbability":0,"temperature":52.14,"apparentTemperature":52.14,"dewPoint":24.94,"humidity":0.34,"windSpeed":12.13,"windBearing":275,"visibility":8.82,"cloudCover":0.27,"pressure":1022.33},"hourly":{"summary":"Partly cloudy starting in the morning, continuing until evening.","icon":"partly-cloudy-day","data":[{"time":947221200,"summary":"Clear","icon":"clear-night","precipIntensity":0,"precipProbability":0,"temperature":33.4,"apparentTemperature":29.22,"dewPoint":29.87,"humidity":0.87,"windSpeed":4.47,"windBearing":202,"visibility":8.82,"cloudCover":0,"pressure":1028.43},{"time":947224800,"summary":"Clear","icon":"clear-night","precipIntensity":0,"precipProbability":0,"temperature":33.88,"apparentTemperature":30.28,"dewPoint":29.45,"humidity":0.84,"windSpeed":3.97,"windBearing":211,"visibility":8.82,"cloudCover":0,"pressure":1027.8},{"time":947228400,"summary":"Partly Cloudy","icon":"partly-cloudy-night","precipIntensity":0,"precipProbability":0,"temperature":32.52,"apparentTemperature":28.63,"dewPoint":29.05,"humidity":0.87,"windSpeed":4.04,"windBearing":210,"visibility":8.82,"cloudCover":0.29,"pressure":1027.23},{"time":947232000,"summary":"Partly Cloudy","icon":"partly-cloudy-night","precipIntensity":0,"precipProbability":0,"temperature":31.77,"apparentTemperature":29.01,"dewPoint":28.34,"humidity":0.87,"windSpeed":3.03,"windBearing":245,"visibility":8.82,"cloudCover":0.29,"pressure":1026.73},{"time":947235600,"summary":"Clear","icon":"clear-night","precipIntensity":0,"precipProbability":0,"temperature":32.01,"apparentTemperature":27.97,"dewPoint":28.61,"humidity":0.87,"windSpeed":4.1,"windBearing":230,"visibility":8.82,"cloudCover":0.05,"pressure":1025.93},{"time":947239200,"summary":"Clear","icon":"clear-night","precipIntensity":0,"precipProbability":0,"temperature":32.19,"apparentTemperature":26.53,"dewPoint":28.16,"humidity":0.85,"windSpeed":5.9,"windBearing":268,"visibility":8.82,"cloudCover":0.02,"pressure":1025.41},{"time":947242800,"summary":"Clear","icon":"clear-night","precipIntensity":0,"precipProbability":0,"temperature":31.2,"apparentTemperature":31.2,"dewPoint":28.17,"humidity":0.88,"windSpeed":2.63,"windBearing":231,"visibility":8.82,"cloudCover":0.08,"pressure":1025.3},{"time":947246400,"summary":"Partly Cloudy","icon":"partly-cloudy-night","precipIntensity":0,"precipProbability":0,"temperature":30.63,"apparentTemperature":30.63,"dewPoint":27.13,"humidity":0.87,"windSpeed":2.54,"windBearing":226,"visibility":8.82,"cloudCover":0.34,"pressure":1024.99},{"time":947250000,"summary":"Mostly Cloudy","icon":"partly-cloudy-day","precipIntensity":0,"precipProbability":0,"temperature":32.8,"apparentTemperature":29.54,"dewPoint":28.75,"humidity":0.85,"windSpeed":3.52,"windBearing":222,"visibility":8.28,"cloudCover":0.75,"pressure":1024.71},{"time":947253600,"summary":"Partly Cloudy","icon":"partly-cloudy-day","precipIntensity":0,"precipProbability":0,"temperature":34.23,"apparentTemperature":29.18,"dewPoint":28.17,"humidity":0.78,"windSpeed":5.62,"windBearing":211,"visibility":8.82,"cloudCover":0.31,"pressure":1024.51},{"time":947257200,"summary":"Partly Cloudy","icon":"partly-cloudy-day","precipIntensity":0,"precipProbability":0,"temperature":39.87,"apparentTemperature":35.92,"dewPoint":30.01,"humidity":0.68,"windSpeed":5.54,"windBearing":214,"visibility":8.82,"cloudCover":0.31,"pressure":1023.28},{"time":947260800,"summary":"Partly Cloudy","icon":"partly-cloudy-day","precipIntensity":0,"precipProbability":0,"temperature":45.13,"apparentTemperature":40.89,"dewPoint":32.31,"humidity":0.61,"windSpeed":7.89,"windBearing":188,"visibility":8.82,"cloudCover":0.29,"pressure":1023.02},{"time":947264400,"summary":"Partly Cloudy","icon":"partly-cloudy-day","precipIntensity":0,"precipProbability":0,"temperature":52.14,"apparentTemperature":52.14,"dewPoint":24.94,"humidity":0.34,"windSpeed":12.13,"windBearing":275,"visibility":8.82,"cloudCover":0.27,"pressure":1022.33},{"time":947268000,"summary":"Partly Cloudy","icon":"partly-cloudy-day","precipIntensity":0,"precipProbability":0,"temperature":54.01,"apparentTemperature":54.01,"dewPoint":25.14,"humidity":0.32,"windSpeed":19.49,"windBearing":279,"visibility":8.82,"cloudCover":0.29,"pressure":1022.74},{"time":947271600,"summary":"Breezy and Partly Cloudy","icon":"wind","precipIntensity":0,"precipProbability":0,"temperature":53.42,"apparentTemperature":53.42,"dewPoint":20.89,"humidity":0.28,"windSpeed":24.5,"windBearing":294,"visibility":8.82,"cloudCover":0.31,"pressure":1022.83},{"time":947275200,"summary":"Partly Cloudy","icon":"partly-cloudy-day","precipIntensity":0,"precipProbability":0,"temperature":53.12,"apparentTemperature":53.12,"dewPoint":20.9,"humidity":0.28,"windSpeed":17.42,"windBearing":290,"visibility":8.82,"cloudCover":0.31,"pressure":1024.21},{"time":947278800,"summary":"Partly Cloudy","icon":"partly-cloudy-day","precipIntensity":0,"precipProbability":0,"temperature":51.96,"apparentTemperature":51.96,"dewPoint":19.19,"humidity":0.27,"windSpeed":17.08,"windBearing":294,"visibility":8.82,"cloudCover":0.31,"pressure":1025.08},{"time":947282400,"summary":"Partly Cloudy","icon":"partly-cloudy-night","precipIntensity":0,"precipProbability":0,"temperature":48.57,"apparentTemperature":42.76,"dewPoint":19.1,"humidity":0.31,"windSpeed":15.22,"windBearing":308,"visibility":8.82,"cloudCover":0.26,"pressure":1024.98},{"time":947286000,"summary":"Clear","icon":"clear-night","precipIntensity":0,"precipProbability":0,"temperature":46.79,"apparentTemperature":41.75,"dewPoint":18.78,"humidity":0.32,"windSpeed":10.86,"windBearing":304,"visibility":8.82,"cloudCover":0,"pressure":1025.62},{"time":947289600,"summary":"Mostly Cloudy","icon":"partly-cloudy-night","precipIntensity":0,"precipProbability":0,"temperature":43.27,"apparentTemperature":43.27,"dewPoint":24.4,"humidity":0.47,"windSpeed":1.48,"windBearing":243,"visibility":8.82,"cloudCover":0.61,"pressure":1025.4},{"time":947293200,"summary":"Clear","icon":"clear-night","precipIntensity":0,"precipProbability":0,"temperature":42.54,"apparentTemperature":39.17,"dewPoint":20.6,"humidity":0.41,"windSpeed":5.42,"windBearing":295,"visibility":8.82,"cloudCover":0,"pressure":1026.91},{"time":947296800,"summary":"Clear","icon":"clear-night","precipIntensity":0,"precipProbability":0,"temperature":40.06,"apparentTemperature":34.44,"dewPoint":20.5,"humidity":0.45,"windSpeed":8.43,"windBearing":305,"visibility":8.82,"cloudCover":0,"pressure":1027.44},{"time":947300400,"summary":"Clear","icon":"clear-night","precipIntensity":0,"precipProbability":0,"temperature":39.08,"apparentTemperature":39.08,"dewPoint":21.37,"humidity":0.49,"windSpeed":2.61,"windBearing":287,"visibility":9.15,"cloudCover":0,"pressure":1028.06},{"time":947304000,"summary":"Clear","icon":"clear-night","precipIntensity":0,"precipProbability":0,"temperature":36.43,"apparentTemperature":36.43,"dewPoint":22.97,"humidity":0.58,"windSpeed":1.89,"windBearing":337,"visibility":8.82,"cloudCover":0,"pressure":1028.32}]},"daily":{"data":[{"time":947221200,"summary":"Partly cloudy until evening.","icon":"partly-cloudy-day","sunriseTime":947248078,"sunsetTime":947282574,"moonPhase":0.03,"precipIntensity":0,"precipIntensityMax":0,"precipProbability":0,"temperatureMin":30.63,"temperatureMinTime":947246400,"temperatureMax":54.01,"temperatureMaxTime":947268000,"apparentTemperatureMin":26.53,"apparentTemperatureMinTime":947239200,"apparentTemperatureMax":54.01,"apparentTemperatureMaxTime":947268000,"dewPoint":25.28,"humidity":0.6,"windSpeed":6.44,"windBearing":275,"visibility":8.81,"cloudCover":0.21,"pressure":1025.47}]},"flags":{"sources":["isd"],"isd-stations":["724030-93738","724035-13773","724037-99999","724050-13743","745940-99999"],"units":"us"}}