{"latitude":38.8048,"longitude":-77.0469,"timezone":"America/New_York","offset":-4,"currently":{"time":1024678800,"summary":"Partly Cloudy","icon":"partly-cloudy-day","precipIntensity":0,"precipProbability":0,"temperature":80.42,"apparentTemperature":80.69,"dewPoint":57.15,"humidity":0.45,"windSpeed":4.82,"windBearing":132,"visibility":8.82,"cloudCover":0.29,"pressure":1031.32},"hourly":{"summary":"Partly cloudy starting in the morning, continuing until night.","icon":"partly-cloudy-day","data":[{"time":1024632000,"summary":"Clear","icon":"clear-night","precipIntensity":0,"precipProbability":0,"temperature":69.98,"apparentTemperature":69.98,"dewPoint":60.23,"humidity":0.71,"windSpeed":7.56,"windBearing":172,"visibility":9.2,"cloudCover":0,"pressure":1030.75},{"time":1024635600,"summary":"Clear","icon":"clear-night","precipIntensity":0,"precipProbability":0,"temperature":67.41,"apparentTemperature":67.41,"dewPoint":60.09,"humidity":0.77,"windSpeed":6,"windBearing":170,"visibility":9.2,"cloudCover":0,"pressure":1031.06},{"time":1024639200,"summary":"Clear","icon":"clear-night","precipIntensity":0,"precipProbability":0,"temperature":66.53,"apparentTemperature":66.53,"dewPoint":60.07,"humidity":0.8,"windSpeed":0.53,"windBearing":151,"visibility":9.2,"cloudCover":0,"pressure":1031.15},{"time":1024642800,"summary":"Clear","icon":"clear-night","precipIntensity":0,"precipProbability":0,"temperature":67.5,"apparentTemperature":67.5,"dewPoint":59.55,"humidity":0.76,"windSpeed":6,"windBearing":300,"visibility":9.71,"pressure":1030.95},{"time":1024646400,"summary":"Clear","icon":"clear-night","precipIntensity":0,"precipProbability":0,"temperature":66.6,"apparentTemperature":66.6,"dewPoint":59.41,"humidity":0.78,"windSpeed":3.81,"windBearing":98,"visibility":9.71,"pressure":1030.75},{"time":1024650000,"summary":"Clear","icon":"clear-night","precipIntensity":0,"precipProbability":0,"temperature":64.9,"apparentTemperature":64.9,"dewPoint":60.54,"humidity":0.86,"windSpeed":2.07,"windBearing":84,"visibility":9.71,"pressure":1030.75},{"time":1024653600,"summary":"Clear","icon":"clear-day","precipIntensity":0,"precipProbability":0,"temperature":63.9,"apparentTemperature":63.9,"dewPoint":59.66,"humidity":0.86,"windSpeed":4.25,"windBearing":67,"visibility":9.71,"pressure":1030.97},{"time":1024657200,"summary":"Clear","icon":"clear-day","precipIntensity":0,"precipProbability":0,"temperature":66,"apparentTemperature":66,"dewPoint":61.43,"humidity":0.85,"windSpeed":4.29,"windBearing":61,"visibility":7.7,"pressure":1031.55},{"time":1024660800,"summary":"Clear","icon":"clear-day","precipIntensity":0,"precipProbability":0,"temperature":67.38,"apparentTemperature":67.38,"dewPoint":62.37,"humidity":0.84,"windSpeed":3.57,"windBearing":66,"visibility":7.84,"cloudCover":0,"pressure":1031.78},{"time":1024664400,"summary":"Clear","icon":"clear-day","precipIntensity":0,"precipProbability":0,"temperature":70.95,"apparentTemperature":70.95,"dewPoint":63.11,"humidity":0.76,"windSpeed":0.63,"windBearing":190,"visibility":8.82,"cloudCover":0.18,"pressure":1032.1},{"time":1024668000,"summary":"Partly Cloudy","icon":"partly-cloudy-day","precipIntensity":0,"precipProbability":0,"temperature":74.42,"apparentTemperature":74.42,"dewPoint":62.34,"humidity":0.66,"windSpeed":1,"windBearing":150,"visibility":8.82,"cloudCover":0.27,"pressure":1032},{"time":1024671600,"summary":"Partly Cloudy","icon":"partly-cloudy-day","precipIntensity":0,"precipProbability":0,"temperature":77.51,"apparentTemperature":77.51,"dewPoint":58.07,"humidity":0.51,"windSpeed":2.8,"windBearing":100,"visibility":8.82,"cloudCover":0.29,"pressure":1031.82},{"time":1024675200,"summary":"Partly Cloudy","icon":"partly-cloudy-day","precipIntensity":0,"precipProbability":0,"temperature":78.87,"apparentTemperature":78.87,"dewPoint":57.27,"humidity":0.48,"windSpeed":4.93,"windBearing":140,"visibility":8.82,"cloudCover":0.31,"pressure":1031.83},{"time":1024678800,"summary":"Partly Cloudy","icon":"partly-cloudy-day","precipIntensity":0,"precipProbability":0,"temperature":80.42,"apparentTemperature":80.69,"dewPoint":57.15,"humidity":0.45,"windSpeed":4.82,"windBearing":132,"visibility":8.82,"cloudCover":0.29,"pressure":1031.32},{"time":1024682400,"summary":"Partly Cloudy","icon":"partly-cloudy-day","precipIntensity":0,"precipProbability":0,"temperature":82.06,"apparentTemperature":81.9,"dewPoint":57.52,"humidity":0.43,"windSpeed":4.3,"windBearing":104,"visibility":8.82,"cloudCover":0.31,"pressure":1030.57},{"time":1024686000,"summary":"Partly Cloudy","icon":"partly-cloudy-day","precipIntensity":0,"precipProbability":0,"temperature":82,"apparentTemperature":81.55,"dewPoint":55.81,"humidity":0.41,"windSpeed":8.02,"windBearing":152,"visibility":8.82,"cloudCover":0.31,"pressure":1029.86},{"time":1024689600,"summary":"Partly Cloudy","icon":"partly-cloudy-day","precipIntensity":0,"precipProbability":0,"temperature":82.41,"apparentTemperature":81.52,"dewPoint":53.91,"humidity":0.38,"windSpeed":7.04,"windBearing":149,"visibility":8.82,"cloudCover":0.31,"pressure":1029.21},{"time":1024693200,"summary":"Partly Cloudy","icon":"partly-cloudy-day","precipIntensity":0,"precipProbability":0,"temperature":82.95,"apparentTemperature":82.11,"dewPoint":55.17,"humidity":0.39,"windSpeed":5.48,"windBearing":160,"visibility":8.82,"cloudCover":0.31,"pressure":1028.74},{"time":1024696800,"summary":"Partly Cloudy","icon":"partly-cloudy-day","precipIntensity":0,"precipProbability":0,"temperature":81.85,"apparentTemperature":81.06,"dewPoint":53.38,"humidity":0.38,"windSpeed":5.95,"windBearing":168,"visibility":8.82,"cloudCover":0.31,"pressure":1028.05},{"time":1024700400,"summary":"Partly Cloudy","icon":"partly-cloudy-day","precipIntensity":0,"precipProbability":0,"temperature":81.17,"apparentTemperature":80.89,"dewPoint":55.21,"humidity":0.41,"windSpeed":2.86,"windBearing":189,"visibility":8.82,"cloudCover":0.31,"pressure":1028.29},{"time":1024704000,"summary":"Mostly Cloudy","icon":"partly-cloudy-day","precipIntensity":0,"precipProbability":0,"temperature":78.34,"apparentTemperature":78.34,"dewPoint":58.49,"humidity":0.51,"windSpeed":5.13,"windBearing":197,"visibility":8.82,"cloudCover":0.68,"pressure":1026.34},{"time":1024707600,"summary":"Partly Cloudy","icon":"partly-cloudy-night","precipIntensity":0,"precipProbability":0,"temperature":75.04,"apparentTemperature":75.04,"dewPoint":60.34,"humidity":0.6,"windSpeed":2.86,"windBearing":205,"visibility":8.82,"cloudCover":0.31,"pressure":1029},{"time":1024711200,"summary":"Partly Cloudy","icon":"partly-cloudy-night","precipIntensity":0,"precipProbability":0,"temperature":72.72,"apparentTemperature":72.72,"dewPoint":61.73,"humidity":0.68,"windSpeed":7.19,"windBearing":171,"visibility":9.2,"cloudCover":0.25,"pressure":1029.35},{"time":1024714800,"summary":"Clear","icon":"clear-night","precipIntensity":0,"precipProbability":0,"temperature":69.61,"apparentTemperature":69.61,"dewPoint":60.72,"humidity":0.73,"windSpeed":6.98,"windBearing":192,"visibility":9.2,"cloudCover":0.03,"pressure":1029.04}]},"daily":{"data":[{"time":1024632000,"summary":"Partly cloudy throughout the day.","icon":"partly-cloudy-day","sunriseTime":1024652680,"sunsetTime":1024706272,"moonPhase":0.39,"precipIntensity":0,"precipIntensityMax":0,"precipProbability":0,"temperatureMin":63.9,"temperatureMinTime":1024653600,"temperatureMax":82.95,"temperatureMaxTime":1024693200,"apparentTemperatureMin":63.9,"apparentTemperatureMinTime":1024653600,"apparentTemperatureMax":82.11,"apparentTemperatureMaxTime":1024693200,"dewPoint":58.9,"humidity":0.63,"windSpeed":3.05,"windBearing":152,"visibility":8.96,"cloudCover":0.24,"pressure":1030.3}]},"flags":{"sources":["isd"],"isd-stations":["724030-93738","724035-13773","724037-99999","724050-13743","745940-99999"],"units":"us"}}