{"latitude":38.8048,"longitude":-77.0469,"timezone":"America/New_York","offset":-4,"currently":{"time":1176397200,"summary":"Partly Cloudy","icon":"partly-cloudy-day","precipIntensity":0,"precipProbability":0,"temperature":55.06,"apparentTemperature":55.06,"dewPoint":47.59,"humidity":0.76,"windSpeed":5,"windBearing":60,"visibility":9.48,"cloudCover":0.39,"pressure":1004.38},"hourly":{"summary":"Rain until morning, starting again in the afternoon.","icon":"rain","data":[{"time":1176350400,"summary":"Rain","icon":"rain","precipIntensity":0.0656,"precipProbability":1,"precipType":"rain","temperature":44.06,"apparentTemperature":41.17,"dewPoint":39.78,"humidity":0.85,"windSpeed":5.11,"windBearing":76,"visibility":4.62,"cloudCover":1,"pressure":1012.92},{"time":1176354000,"summary":"Rain","icon":"rain","precipIntensity":0.1476,"precipProbability":1,"precipType":"rain","temperature":44.06,"apparentTemperature":37.95,"dewPoint":41.72,"humidity":0.91,"windSpeed":12.02,"windBearing":89,"visibility":5.38,"cloudCover":0.95,"pressure":1010.41},{"time":1176357600,"summary":"Light Rain","icon":"rain","precipIntensity":0.0228,"precipProbability":0.76,"precipType":"rain","temperature":45,"apparentTemperature":39.86,"dewPoint":43.78,"humidity":0.95,"windSpeed":9.95,"windBearing":83,"visibility":3.17,"cloudCover":0.86,"pressure":1008.66},{"time":1176361200,"summary":"Rain","icon":"rain","precipIntensity":0.1204,"precipProbability":1,"precipType":"rain","temperature":46,"apparentTemperature":42.73,"dewPoint":45.3,"humidity":0.97,"windSpeed":6.32,"windBearing":108,"visibility":4.79,"cloudCover":1,"pressure":1006.9},{"time":1176364800,"summary":"Rain","icon":"rain","precipIntensity":0.1,"precipProbability":1,"precipType":"rain","temperature":46,"apparentTemperature":44.68,"dewPoint":46,"humidity":1,"windSpeed":3.49,"windBearing":30,"visibility":2.43,"cloudCover":0.86,"pressure":1006.21},{"time":1176368400,"summary":"Rain","icon":"rain","precipIntensity":0.1124,"precipProbability":1,"precipType":"rain","temperature":46.41,"apparentTemperature":41.45,"dewPoint":46.41,"humidity":1,"windSpeed":10.37,"windBearing":324,"visibility":3.86,"cloudCover":0.95,"pressure":1006.14},{"time":1176372000,"summary":"Light Rain","icon":"rain","precipIntensity":0.024,"precipProbability":0.24,"precipType":"rain","temperature":45.88,"apparentTemperature":41.22,"dewPoint":45.31,"humidity":0.98,"windSpeed":9.26,"windBearing":17,"visibility":6.39,"cloudCover":0.91,"pressure":1006.51},{"time":1176375600,"summary":"Light Rain","icon":"rain","precipIntensity":0.01,"precipProbability":1,"precipType":"rain","temperature":45.88,"apparentTemperature":41.79,"dewPoint":45.12,"humidity":0.97,"windSpeed":7.91,"windBearing":8,"visibility":9.48,"cloudCover":0.96,"pressure":1005.64},{"time":1176379200,"summary":"Overcast","icon":"cloudy","precipIntensity":0,"precipProbability":0,"temperature":46.54,"apparentTemperature":42.28,"dewPoint":45.52,"humidity":0.96,"windSpeed":8.63,"windBearing":336,"visibility":9.48,"cloudCover":1,"pressure":1006.3},{"time":1176382800,"summary":"Overcast","icon":"cloudy","precipIntensity":0,"precipProbability":0,"temperature":47.42,"apparentTemperature":44.35,"dewPoint":45.81,"humidity":0.94,"windSpeed":6.47,"windBearing":13,"visibility":9.48,"cloudCover":1,"pressure":1005.84},{"time":1176386400,"summary":"Overcast","icon":"cloudy","precipIntensity":0,"precipProbability":0,"temperature":48.89,"apparentTemperature":47.09,"dewPoint":45.86,"humidity":0.89,"windSpeed":4.72,"windBearing":45,"visibility":9.48,"cloudCover":1,"pressure":1005.48},{"time":1176390000,"summary":"Overcast","icon":"cloudy","precipIntensity":0,"precipProbability":0,"temperature":50.35,"apparentTemperature":50.35,"dewPoint":46.57,"humidity":0.87,"windSpeed":2.43,"windBearing":357,"visibility":8.83,"cloudCover":1,"pressure":1005.45},{"time":1176393600,"summary":"Overcast","icon":"cloudy","precipIntensity":0,"precipProbability":0,"temperature":51.98,"apparentTemperature":51.98,"dewPoint":47.52,"humidity":0.85,"windSpeed":4.43,"windBearing":305,"visibility":9.48,"cloudCover":0.96,"pressure":1005.33},{"time":1176397200,"summary":"Partly Cloudy","icon":"partly-cloudy-day","precipIntensity":0,"precipProbability":0,"temperature":55.06,"apparentTemperature":55.06,"dewPoint":47.59,"humidity":0.76,"windSpeed":5,"windBearing":60,"visibility":9.48,"cloudCover":0.39,"pressure":1004.38},{"time":1176400800,"summary":"Partly Cloudy","icon":"partly-cloudy-day","precipIntensity":0,"precipProbability":0,"temperature":58.15,"apparentTemperature":58.15,"dewPoint":48.58,"humidity":0.7,"windSpeed":3.08,"windBearing":37,"visibility":9.48,"cloudCover":0.26,"pressure":1004.05},{"time":1176404400,"summary":"Mostly Cloudy","icon":"partly-cloudy-day","precipIntensity":0,"precipProbability":0,"temperature":61.76,"apparentTemperature":61.76,"dewPoint":48.72,"humidity":0.62,"windSpeed":3.21,"windBearing":57,"visibility":9.48,"cloudCover":0.65,"pressure":1003.5},{"time":1176408000,"summary":"Rain","icon":"rain","precipIntensity":0.09,"precipProbability":1,"precipType":"rain","temperature":56.17,"apparentTemperature":56.17,"dewPoint":49.4,"humidity":0.78,"windSpeed":4.52,"windBearing":334,"visibility":8.59,"cloudCover":0.91,"pressure":1003.76},{"time":1176411600,"summary":"Rain","icon":"rain","precipIntensity":0.0924,"precipProbability":1,"precipType":"rain","temperature":57.48,"apparentTemperature":57.48,"dewPoint":51.48,"humidity":0.8,"windSpeed":1.81,"windBearing":286,"visibility":9.48,"cloudCover":0.62,"pressure":1004.07},{"time":1176415200,"summary":"Mostly Cloudy","icon":"partly-cloudy-day","precipIntensity":0,"precipProbability":0,"temperature":58.05,"apparentTemperature":58.05,"dewPoint":45.86,"humidity":0.64,"windSpeed":16.94,"windBearing":324,"visibility":9.48,"cloudCover":0.62,"pressure":1005.08},{"time":1176418800,"summary":"Partly Cloudy","icon":"partly-cloudy-day","precipIntensity":0,"precipProbability":0,"temperature":56.23,"apparentTemperature":56.23,"dewPoint":43.87,"humidity":0.63,"windSpeed":10.57,"windBearing":326,"visibility":9.48,"cloudCover":0.59,"pressure":1006.46},{"time":1176422400,"summary":"Clear","icon":"clear-night","precipIntensity":0,"precipProbability":0,"temperature":52.89,"apparentTemperature":52.89,"dewPoint":28.44,"humidity":0.39,"windSpeed":8.06,"windBearing":306,"visibility":9.48,"cloudCover":0.17,"pressure":1017.6},{"time":1176426000,"summary":"Clear","icon":"clear-night","precipIntensity":0,"precipProbability":0,"temperature":53.29,"apparentTemperature":53.29,"dewPoint":36.47,"humidity":0.53,"windSpeed":15.37,"windBearing":310,"visibility":9.48,"cloudCover":0.22,"pressure":1008.68},{"time":1176429600,"summary":"Partly Cloudy","icon":"partly-cloudy-night","precipIntensity":0,"precipProbability":0,"temperature":52.65,"apparentTemperature":52.65,"dewPoint":34.23,"humidity":0.49,"windSpeed":15.53,"windBearing":310,"visibility":10,"cloudCover":0.25,"pressure":1010.06},{"time":1176433200,"summary":"Partly Cloudy","icon":"partly-cloudy-night","precipIntensity":0,"precipProbability":0,"temperature":51.14,"apparentTemperature":51.14,"dewPoint":33.78,"humidity":0.51,"windSpeed":13.55,"windBearing":308,"visibility":10,"cloudCover":0.31,"pressure":1010.38}]},"daily":{"data":[{"time":1176350400,"summary":"Rain in the morning and afternoon.","icon":"rain","sunriseTime":1176374251,"sunsetTime":1176421357,"moonPhase":0.82,"precipIntensity":0.0327,"precipIntensityMax":0.1476,"precipIntensityMaxTime":1176354000,"precipProbability":1,"precipType":"rain","temperatureMin":44.06,"temperatureMinTime":1176354000,"temperatureMax":61.76,"temperatureMaxTime":1176404400,"apparentTemperatureMin":37.95,"apparentTemperatureMinTime":1176354000,"apparentTemperatureMax":61.76,"apparentTemperatureMaxTime":1176404400,"dewPoint":43.88,"humidity":0.79,"windSpeed":5.01,"windBearing":350,"visibility":7.97,"cloudCover":0.73,"pressure":1007.08}]},"flags":{"sources":["isd"],"isd-stations":["722244-99999","724037-93728","724050-13743","745940-13705","997314-99999"],"units":"us"}}