{"latitude":38.8048,"longitude":-77.0469,"timezone":"America/New_York","offset":-4,"currently":{"time":1368032400,"summary":"Partly Cloudy","icon":"partly-cloudy-day","precipIntensity":0,"precipProbability":0,"temperature":66.6,"apparentTemperature":66.6,"dewPoint":56.05,"humidity":0.69,"windSpeed":4.2,"windBearing":171,"visibility":10,"cloudCover":0.31,"pressure":1015.48},"hourly":{"summary":"Rain starting later this afternoon, continuing until this evening.","icon":"rain","data":[{"time":1367985600,"summary":"Overcast","icon":"cloudy","precipIntensity":0.0049,"precipProbability":0.24,"precipType":"rain","temperature":61.47,"apparentTemperature":61.47,"dewPoint":58.44,"humidity":0.9,"windSpeed":3.88,"windBearing":133,"visibility":8.7,"cloudCover":1,"pressure":1015.22},{"time":1367989200,"summary":"Mostly Cloudy","icon":"partly-cloudy-night","precipIntensity":0,"precipProbability":0,"temperature":60.68,"apparentTemperature":60.68,"dewPoint":57.78,"humidity":0.9,"windSpeed":3.46,"windBearing":95,"visibility":8.49,"cloudCover":0.88,"pressure":1015.35},{"time":1367992800,"summary":"Overcast","icon":"cloudy","precipIntensity":0,"precipProbability":0,"temperature":60.24,"apparentTemperature":60.24,"dewPoint":57.84,"humidity":0.92,"windSpeed":3.23,"windBearing":97,"visibility":9.65,"cloudCover":1,"pressure":1014.97},{"time":1367996400,"summary":"Overcast","icon":"cloudy","precipIntensity":0,"precipProbability":0,"temperature":59.98,"apparentTemperature":59.98,"dewPoint":57.95,"humidity":0.93,"windSpeed":4.25,"windBearing":90,"visibility":9.84,"cloudCover":1,"pressure":1014.34},{"time":1368000000,"summary":"Overcast","icon":"cloudy","precipIntensity":0,"precipProbability":0,"temperature":60.11,"apparentTemperature":60.11,"dewPoint":57.71,"humidity":0.92,"windSpeed":4.17,"windBearing":99,"visibility":9.49,"cloudCover":1,"pressure":1014.64},{"time":1368003600,"summary":"Overcast","icon":"cloudy","precipIntensity":0,"precipProbability":0,"temperature":59.71,"apparentTemperature":59.71,"dewPoint":57.11,"humidity":0.91,"windSpeed":4.68,"windBearing":84,"visibility":8.43,"cloudCover":1,"pressure":1014.55},{"time":1368007200,"summary":"Overcast","icon":"cloudy","precipIntensity":0,"precipProbability":0,"temperature":59.59,"apparentTemperature":59.59,"dewPoint":57.19,"humidity":0.92,"windSpeed":3.37,"windBearing":85,"visibility":8.78,"cloudCover":1,"pressure":1014.68},{"time":1368010800,"summary":"Overcast","icon":"cloudy","precipIntensity":0,"precipProbability":0,"temperature":59.46,"apparentTemperature":59.46,"dewPoint":57.22,"humidity":0.92,"windSpeed":2.78,"windBearing":66,"visibility":9.49,"cloudCover":1,"pressure":1015.14},{"time":1368014400,"summary":"Overcast","icon":"cloudy","precipIntensity":0,"precipProbability":0,"temperature":61.2,"apparentTemperature":61.2,"dewPoint":56.09,"humidity":0.83,"windSpeed":4.09,"windBearing":56,"visibility":10,"cloudCover":1,"pressure":1015.77},{"time":1368018000,"summary":"Overcast","icon":"cloudy","precipIntensity":0,"precipProbability":0,"temperature":61.72,"apparentTemperature":61.72,"dewPoint":56.25,"humidity":0.82,"windSpeed":2.47,"windBearing":69,"visibility":10,"cloudCover":1,"pressure":1016.15},{"time":1368021600,"summary":"Overcast","icon":"cloudy","precipIntensity":0,"precipProbability":0,"temperature":62.32,"apparentTemperature":62.32,"dewPoint":55.77,"humidity":0.79,"windSpeed":2.06,"windBearing":85,"visibility":10,"cloudCover":1,"pressure":1016.32},{"time":1368025200,"summary":"Overcast","icon":"cloudy","precipIntensity":0,"precipProbability":0,"temperature":63.78,"apparentTemperature":63.78,"dewPoint":55.62,"humidity":0.75,"windSpeed":2.64,"windBearing":172,"visibility":10,"cloudCover":1,"pressure":1016.34},{"time":1368028800,"summary":"Partly Cloudy","icon":"partly-cloudy-day","precipIntensity":0,"precipProbability":0,"temperature":64.92,"apparentTemperature":64.92,"dewPoint":55.31,"humidity":0.71,"windSpeed":2.89,"windBearing":165,"visibility":10,"cloudCover":0.31,"pressure":1016.05},{"time":1368032400,"summary":"Partly Cloudy","icon":"partly-cloudy-day","precipIntensity":0,"precipProbability":0,"temperature":66.6,"apparentTemperature":66.6,"dewPoint":56.05,"humidity":0.69,"windSpeed":4.2,"windBearing":171,"visibility":10,"cloudCover":0.31,"pressure":1015.48},{"time":1368036000,"summary":"Partly Cloudy","icon":"partly-cloudy-day","precipIntensity":0,"precipProbability":0,"temperature":68.12,"apparentTemperature":68.12,"dewPoint":55.74,"humidity":0.65,"windSpeed":5.95,"windBearing":182,"visibility":9.41,"cloudCover":0.31,"pressure":1014.84},{"time":1368039600,"summary":"Partly Cloudy","icon":"partly-cloudy-day","precipIntensity":0.0024,"precipProbability":0.24,"precipType":"rain","temperature":70.26,"apparentTemperature":70.26,"dewPoint":54.23,"humidity":0.57,"windSpeed":6.74,"windBearing":175,"visibility":10,"cloudCover":0.31,"pressure":1013.98},{"time":1368043200,"summary":"Drizzle","icon":"rain","precipIntensity":0.0077,"precipProbability":0.19,"precipType":"rain","temperature":65.1,"apparentTemperature":65.1,"dewPoint":55.09,"humidity":0.7,"windSpeed":12.7,"windBearing":174,"visibility":7.73,"cloudCover":0.88,"pressure":1014.08},{"time":1368046800,"summary":"Rain","icon":"rain","precipIntensity":0.0856,"precipProbability":0.39,"precipType":"rain","temperature":61.41,"apparentTemperature":61.41,"dewPoint":55.61,"humidity":0.81,"windSpeed":7.58,"windBearing":193,"visibility":9.05,"cloudCover":0.86,"pressure":1014.95},{"time":1368050400,"summary":"Light Rain","icon":"rain","precipIntensity":0.012,"precipProbability":1,"precipType":"rain","temperature":60.93,"apparentTemperature":60.93,"dewPoint":55.49,"humidity":0.82,"windSpeed":5.22,"windBearing":204,"visibility":9.85,"cloudCover":0.9,"pressure":1015.05},{"time":1368054000,"summary":"Light Rain","icon":"rain","precipIntensity":0.0136,"precipProbability":0.39,"precipType":"rain","temperature":60.11,"apparentTemperature":60.11,"dewPoint":56.07,"humidity":0.87,"windSpeed":5.14,"windBearing":204,"visibility":10,"cloudCover":1,"pressure":1014.75},{"time":1368057600,"summary":"Partly Cloudy","icon":"partly-cloudy-day","precipIntensity":0.0024,"precipProbability":0.24,"precipType":"rain","temperature":65.88,"apparentTemperature":65.88,"dewPoint":60.22,"humidity":0.82,"windSpeed":4.15,"windBearing":196,"visibility":10,"cloudCover":0.31,"pressure":1014.86},{"time":1368061200,"summary":"Mostly Cloudy","icon":"partly-cloudy-night","precipIntensity":0,"precipProbability":0,"temperature":58.63,"apparentTemperature":58.63,"dewPoint":56.25,"humidity":0.92,"windSpeed":3.36,"windBearing":207,"visibility":7.9,"cloudCover":0.6,"pressure":1014.85},{"time":1368064800,"summary":"Mostly Cloudy","icon":"partly-cloudy-night","precipIntensity":0,"precipProbability":0,"temperature":58.91,"apparentTemperature":58.91,"dewPoint":56.03,"humidity":0.9,"windSpeed":2.81,"windBearing":132,"visibility":8.42,"cloudCover":0.72,"pressure":1015.32},{"time":1368068400,"summary":"Overcast","icon":"cloudy","precipIntensity":0,"precipProbability":0,"temperature":58.07,"apparentTemperature":58.07,"dewPoint":55.69,"humidity":0.92,"windSpeed":1.08,"windBearing":205,"visibility":8.13,"cloudCover":1,"pressure":1015.31}]},"daily":{"data":[{"time":1367985600,"summary":"Rain starting in the afternoon, continuing until evening.","icon":"rain","sunriseTime":1368007420,"sunsetTime":1368058095,"moonPhase":0.96,"precipIntensity":0.0054,"precipIntensityMax":0.0856,"precipIntensityMaxTime":1368046800,"precipProbability":1,"precipType":"rain","temperatureMin":58.07,"temperatureMinTime":1368068400,"temperatureMax":70.26,"temperatureMaxTime":1368039600,"apparentTemperatureMin":58.07,"apparentTemperatureMinTime":1368068400,"apparentTemperatureMax":70.26,"apparentTemperatureMaxTime":1368039600,"dewPoint":56.53,"humidity":0.83,"windSpeed":2.86,"windBearing":151,"visibility":9.31,"cloudCover":0.81,"pressure":1015.12}]},"flags":{"sources":["isd"],"isd-stations":["722244-99999","724037-93728","724050-13743","745940-13705","997314-99999"],"units":"us"}}